ipyrest/__init__.py
ipyrest/codegen.py
ipyrest/extendedtab.py
ipyrest/ipyrest.py
ipyrest/responseviews.py
ipyrest/utils.py
ipyrest-0.1.4.dist-info/AUTHORS.rst
ipyrest-0.1.4.dist-info/LICENSE
ipyrest-0.1.4.dist-info/METADATA
ipyrest-0.1.4.dist-info/WHEEL
ipyrest-0.1.4.dist-info/top_level.txt
ipyrest-0.1.4.dist-info/RECORD
