Metadata-Version: 2.1
Name: ipyrest
Version: 0.1.4
Summary: An emerging widget for exploring RESTful APIs in Jupyter notebooks.
Home-page: https://github.com/deeplook/ipyrest
Author: Dinu Gherman
Author-email: gherman@darwin.in-berlin.de
License: MIT license
Keywords: ipyrest
Platform: UNKNOWN
Classifier: Development Status :: 3 - Alpha
Classifier: Intended Audience :: Developers
Classifier: License :: OSI Approved :: MIT License
Classifier: Natural Language :: English
Classifier: Programming Language :: Python :: 3
Classifier: Programming Language :: Python :: 3.6
Classifier: Programming Language :: Python :: 3.7
Classifier: Programming Language :: Python :: 3.8
Requires-Dist: ipywidgets (>=7.4.2)
Requires-Dist: jinja2
Requires-Dist: requests
Requires-Dist: timeout-decorator
Requires-Dist: typing
Requires-Dist: vcrpy
Requires-Dist: geojson
Requires-Dist: gpxpy
Requires-Dist: ipyleaflet
Requires-Dist: ipyvolume (>=0.5.1)
Requires-Dist: numpy
Requires-Dist: pandas
Requires-Dist: protobuf
Requires-Dist: qgrid
